tekdate/__init__.py
tekdate/module.py
tekdate-0.1.dist-info/METADATA
tekdate-0.1.dist-info/WHEEL
tekdate-0.1.dist-info/top_level.txt
tekdate-0.1.dist-info/RECORD
