Metadata-Version: 2.1
Name: tekdate
Version: 0.1
Summary: tekdate format is a clear, human-readable date format designed to simplify global date handling and eliminate regional confusion.
Home-page: https://github.com/frkntkny/tekdate
Author: Furkan Tekinay
Author-email: tekinayfurkan@gmail.com
Classifier: Programming Language :: Python :: 3
Classifier: License :: OSI Approved :: MIT License
Classifier: Operating System :: OS Independent
Requires-Python: >=3.6
